pyrcel/__init__.py
pyrcel/_parcel_aux_numba.py
pyrcel/activation.py
pyrcel/aerosol.py
pyrcel/constants.py
pyrcel/distributions.py
pyrcel/driver.py
pyrcel/integrator.py
pyrcel/output.py
pyrcel/parcel.py
pyrcel/postprocess.py
pyrcel/thermo.py
pyrcel/util.py
pyrcel/version.py
pyrcel/vis.py
pyrcel/data/std_atm.csv
pyrcel/scripts/__init__.py
pyrcel/scripts/run_parcel.py
pyrcel/test/__init__.py
pyrcel/test/generate_data.py
pyrcel/test/pm_test.py
pyrcel/test/results.dict
pyrcel/test/test_thermo.py
pyrcel-1.3.4.dist-info/licenses/LICENSE.md
pyrcel-1.3.4.dist-info/METADATA
pyrcel-1.3.4.dist-info/WHEEL
pyrcel-1.3.4.dist-info/entry_points.txt
pyrcel-1.3.4.dist-info/top_level.txt
pyrcel-1.3.4.dist-info/RECORD
