Metadata-Version: 2.4
Name: pyrcel
Version: 1.3.4
Summary: pyrcel: 0D adiabatic cloud parcel model
Author-email: Daniel Rothenberg <daniel@danielrothenberg.com>
License: Copyright (c) Daniel Rothenberg, 2012-2019
Project-URL: Documentation, https://pyrcel.readthedocs.io/en/latest/
Project-URL: Repository, https://github.com/darothen/pyrcel
Classifier: Development Status :: 5 - Production/Stable
Classifier: Environment :: Console
Classifier: Intended Audience :: Science/Research
Classifier: License :: OSI Approved :: BSD License
Classifier: Natural Language :: English
Classifier: Operating System :: Unix
Classifier: Programming Language :: Python :: 3.8
Classifier: Programming Language :: Python :: 3.9
Classifier: Programming Language :: Python :: 3.10
Classifier: Programming Language :: Python :: 3.11
Classifier: Programming Language :: Python :: 3.12
Classifier: Topic :: Scientific/Engineering :: Atmospheric Science
Requires-Python: <3.13,>=3.8
License-File: LICENSE.md
Requires-Dist: numba
Requires-Dist: numpy
Requires-Dist: pandas
Requires-Dist: pyyaml
Requires-Dist: scipy
Requires-Dist: setuptools
Requires-Dist: setuptools-scm
Requires-Dist: xarray
Dynamic: license-file
